pygeoc/TauDEM.py
pygeoc/__init__.py
pygeoc/hydro.py
pygeoc/postTauDEM.py
pygeoc/raster.py
pygeoc/utils.py
pygeoc/vector.py
PyGeoC-0.3.1.dist-info/LICENSE
PyGeoC-0.3.1.dist-info/METADATA
PyGeoC-0.3.1.dist-info/WHEEL
PyGeoC-0.3.1.dist-info/entry_points.txt
PyGeoC-0.3.1.dist-info/top_level.txt
PyGeoC-0.3.1.dist-info/RECORD
